ea_model/__init__.py
ea_model/cli/__init__.py
ea_model/cli/ea_test_cli.py
ea_model/model/__init__.py
ea_model/model/ea/__init__.py
ea_model/model/ea/collection.py
ea_model/model/ea/diagram.py
ea_model/model/ea/element.py
ea_model/model/ea/exception.py
ea_model/model/ea/instance.py
ea_model/model/ea/type_def.py
py_ea_model-0.1.0.dist-info/LICENSE
py_ea_model-0.1.0.dist-info/METADATA
py_ea_model-0.1.0.dist-info/WHEEL
py_ea_model-0.1.0.dist-info/entry_points.txt
py_ea_model-0.1.0.dist-info/top_level.txt
py_ea_model-0.1.0.dist-info/RECORD
