Metadata-Version: 2.1
Name: py-ea-model
Version: 0.1.0
Summary: The assistant tool for the Enterprise Architect
Home-page: https://github.com/melodypapa/py-ea-model
Author: melodypapa
Author-email: melodypapa@outlook.com
License: proprietary
Keywords: Enterprise Architect,UML,EA
Platform: UNKNOWN
Classifier: Development Status :: 1 - Planning
Classifier: Environment :: Console
Classifier: Programming Language :: Python :: 3
Classifier: License :: OSI Approved :: MIT License
Classifier: Operating System :: OS Independent
Requires-Dist: armodel
Requires-Dist: pywin32
Requires-Dist: openpyxl
Provides-Extra: pytest
Requires-Dist: pytest-cov ; extra == 'pytest'
